autoplugin/__init__.py
autoplugin/autoplugin.py
autoplugin/basic_app.py
autoplugin/testing.py
autoplugin-0.1.5.dist-info/LICENSE
autoplugin-0.1.5.dist-info/METADATA
autoplugin-0.1.5.dist-info/WHEEL
autoplugin-0.1.5.dist-info/top_level.txt
autoplugin-0.1.5.dist-info/RECORD
