Metadata-Version: 2.1
Name: autoplugin
Version: 0.1.5
Summary: Create ChatGPT plugins from Python code
Home-page: https://github.com/suvansh/autoplugin
Author: Suvansh Sanjeev
Author-email: suvansh@brilliantly.ai
Project-URL: Tracker, https://github.com/suvansh/autoplugin/issues
Project-URL: Source, https://github.com/suvansh/autoplugin/
Project-URL: Blog, https://brilliantly.ai/blog/autoplugin
Project-URL: Documentation, https://github.com/suvansh/AutoPlugin/blob/main/README.md
Classifier: Development Status :: 3 - Alpha
Classifier: License :: OSI Approved :: BSD License
Classifier: Programming Language :: Python :: 3
Classifier: Programming Language :: Python :: 3.7
Classifier: Programming Language :: Python :: 3.8
Classifier: Programming Language :: Python :: 3.9
Classifier: Programming Language :: Python :: 3.10
License-File: LICENSE
Requires-Dist: fastapi
Requires-Dist: pydantic
Requires-Dist: uvicorn
Requires-Dist: requests
Requires-Dist: PyYAML
Provides-Extra: gen
Requires-Dist: langchain ; extra == 'gen'
